{"cameraMode":{"drawMode":0,"name":"Shaded","section":"Shading Mode"},"sceneLighting":false,"audioPlay":false,"sceneViewState":{"m_AlwaysRefresh":false,"showFog":true,"showSkybox":false,"showFlares":true,"showImageEffects":true,"showParticleSystems":true,"showVisualEffectGraphs":true,"m_FxEnabled":true},"in2DMode":false,"pivot":{"x":6.053920745849609,"y":-2.467775821685791,"z":6.3002848625183109},"rotation":{"x":-0.13264042139053346,"y":-0.8325663805007935,"z":0.48824018239974978,"w":-0.22606594860553742},"size":14.142135620117188,"orthographic":false}